deb_subscription-0.0.0.2.data/scripts/deb_subscription
deb_subscription_lib/__init__.py
deb_subscription_lib/models.py
deb_subscription_lib/utils.py
deb_subscription_lib/templates/__init__.py
deb_subscription_lib/templates/custom-apt-conf.j2
deb_subscription-0.0.0.2.dist-info/LICENSE
deb_subscription-0.0.0.2.dist-info/METADATA
deb_subscription-0.0.0.2.dist-info/WHEEL
deb_subscription-0.0.0.2.dist-info/top_level.txt
deb_subscription-0.0.0.2.dist-info/RECORD
