Metadata-Version: 2.1
Name: deb-subscription
Version: 0.0.0.2
Summary: A tool for to add katello repositories to debian hosts and to register debian host to katello
Home-page: https://github.com/smehboub/deb_subscription
Author: Sophian Mehboub
Author-email: sophienmehboub@gmail.com
License: UNKNOWN
Platform: UNKNOWN
Classifier: Programming Language :: Python :: 2
Classifier: Programming Language :: Python :: 3
Classifier: License :: OSI Approved :: GNU General Public License v3 (GPLv3)
Classifier: Operating System :: POSIX :: Linux
Requires-Dist: requests
Requires-Dist: python-gnupg
Requires-Dist: jinja2
Requires-Dist: docopts
